ciel/__init__.py
ciel/bounds.py
ciel/classifier/cnn_puyo_classifier.py
ciel/collection/__init__.py
ciel/collection/bidirectional_multimap.py
ciel/collection/counting_queue.py
ciel/collection/dag.py
ciel/common.py
ciel/gamerule/__init__.py
ciel/gamerule/chain.py
ciel/gamerule/field.py
ciel/gamerule/field_transition.py
ciel/gamerule/record_serializer.py
ciel/movie_parser.py
ciel/recognizer/__init__.py
ciel/recognizer/field_recognizer.py
ciel/recognizer/game_state_recognizer.py
ciel/recognizer/next_recognizer.py
ciel/recognizer/score_recognizer.py
ciel/score_template_matching.py
ciel/transition/__init__.py
ciel/transition/snapshot.py
ciel/transition/snapshot_graph.py
ciel/util/__init__.py
ciel/util/time.py
ciel/video/__init__.py
ciel/video/video_reader.py
ciel/video/video_writer.py
models/README.md
models/cnn/saved_model.pb
models/cnn/variables/variables.data-00000-of-00002
models/cnn/variables/variables.data-00001-of-00002
models/cnn/variables/variables.index
models/score_template.pickle
scripts/analyze_video.py
asai_ciel-1.0.6.dist-info/entry_points.txt
asai_ciel-1.0.6.dist-info/WHEEL
asai_ciel-1.0.6.dist-info/METADATA
asai_ciel-1.0.6.dist-info/RECORD
