Metadata-Version: 2.1
Name: asai-ciel
Version: 1.0.6
Summary: 
Author: haripo
Author-email: haripo@users.noreply.github.com
Requires-Python: >=3.9,<4.0
Classifier: Programming Language :: Python :: 3
Classifier: Programming Language :: Python :: 3.9
Requires-Dist: asai-abyss (>=0.3.2,<0.4.0)
Requires-Dist: click (>=7.0)
Requires-Dist: colorama (>=0.4.4,<0.5.0)
Requires-Dist: opencv-python-headless (>=4.0,<5.0)
Requires-Dist: pandas (>=1.3.1,<2.0.0)
Requires-Dist: scikit-learn (>=0.24.2,<0.25.0)
Requires-Dist: tensorflow (>=2.5.0,<3.0.0)
Requires-Dist: tqdm (>=4.62.0,<5.0.0)
